compchem_si/__init__.py
compchem_si/si_generation.py
compchem_si-0.1.0.dist-info/LICENSE
compchem_si-0.1.0.dist-info/WHEEL
compchem_si-0.1.0.dist-info/METADATA
compchem_si-0.1.0.dist-info/RECORD
