Metadata-Version: 2.1
Name: compchem-si
Version: 0.1.0
Summary: A plugin for generating SI data from Gaussian output files
Keywords: gaussian,electronic structure calculations
Author-email: Kevin Lefrancois-Gagnon <kgagnon@lakeheadu.ca>, Robert Mawhinney <rmawhinn@lakeheadu.ca>
Requires-Python: >=3.10
Classifier: Programming Language :: Python
Classifier: Programming Language :: Python :: 3
Classifier: Programming Language :: Python :: 3.10
Classifier: Programming Language :: Python :: 3.11
Classifier: Programming Language :: Python :: 3.12
Classifier: Intended Audience :: Science/Research
Classifier: License :: OSI Approved :: MIT License
Classifier: Natural Language :: English
Classifier: Development Status :: 3 - Alpha
Requires-Dist: numpy
Requires-Dist: pandas
Requires-Dist: pillow
Requires-Dist: mogli
Requires-Dist: reportlab
Requires-Dist: cclib
Requires-Dist: sphinx ; extra == "docs"
Requires-Dist: sphinxcontrib-contentui ; extra == "docs"
Requires-Dist: sphinxcontrib-details-directive ; extra == "docs"
Requires-Dist: furo ; extra == "docs"
Requires-Dist: markupsafe<2.1 ; extra == "docs"
Requires-Dist: pandas ; extra == "docs"
Requires-Dist: numpy ; extra == "docs"
Requires-Dist: sphinx-rtd-theme ; extra == "docs"
Requires-Dist: pre-commit~=2.2 ; extra == "pre-commit"
Requires-Dist: pylint~=2.15.10 ; extra == "pre-commit"
Requires-Dist: pgtest~=1.3.1 ; extra == "testing"
Requires-Dist: wheel~=0.31 ; extra == "testing"
Requires-Dist: coverage ; extra == "testing"
Requires-Dist: pytest~=6.0 ; extra == "testing"
Requires-Dist: pytest-cov ; extra == "testing"
Requires-Dist: pytest-regressions~=2.3 ; extra == "testing"
Requires-Dist: coveralls ; extra == "testing"
Project-URL: Source, https://github.com/kmlefran/compchem-si
Provides-Extra: docs
Provides-Extra: pre-commit
Provides-Extra: testing
